ola_plug/OLAPlugDLLHelper.py
ola_plug/OLAPlugServer.py
ola_plug/__init__.py
ola_plug-1.0.0.dist-info/licenses/LICENSE
ola_plug-1.0.0.dist-info/METADATA
ola_plug-1.0.0.dist-info/WHEEL
ola_plug-1.0.0.dist-info/top_level.txt
ola_plug-1.0.0.dist-info/RECORD
