Metadata-Version: 2.4
Name: ola_plug
Version: 1.0.0
Summary: OLA Plug DLL Helper - Python wrapper for OLAPlug DLL
Author: OLA Plug Team
License: MIT
Project-URL: Homepage, https://github.com/ola-plug/ola_plug
Project-URL: Repository, https://github.com/ola-plug/ola_plug
Project-URL: Issues, https://github.com/ola-plug/ola_plug/issues
Keywords: ola,plug,dll,automation,windows
Classifier: Development Status :: 4 - Beta
Classifier: Intended Audience :: Developers
Classifier: License :: OSI Approved :: MIT License
Classifier: Operating System :: Microsoft :: Windows
Classifier: Programming Language :: Python :: 3
Classifier: Programming Language :: Python :: 3.7
Classifier: Programming Language :: Python :: 3.8
Classifier: Programming Language :: Python :: 3.9
Classifier: Programming Language :: Python :: 3.10
Classifier: Programming Language :: Python :: 3.11
Classifier: Programming Language :: Python :: 3.12
Classifier: Topic :: Software Development :: Libraries :: Python Modules
Requires-Python: >=3.7
License-File: LICENSE
Dynamic: license-file
